pypose_sphinx_theme.py
pypose_sphinx_theme/__init__.py
pypose_sphinx_theme/breadcrumbs.html
pypose_sphinx_theme/cookie_banner.html
pypose_sphinx_theme/fonts.html
pypose_sphinx_theme/footer.html
pypose_sphinx_theme/layout.html
pypose_sphinx_theme/search.html
pypose_sphinx_theme/searchbox.html
pypose_sphinx_theme/theme.conf
pypose_sphinx_theme/theme_variables.jinja
pypose_sphinx_theme/versions.html
pypose_sphinx_theme/static/css/theme.css
pypose_sphinx_theme/static/fonts/FreightSans/freight-sans-bold-italic.woff
pypose_sphinx_theme/static/fonts/FreightSans/freight-sans-bold-italic.woff2
pypose_sphinx_theme/static/fonts/FreightSans/freight-sans-bold.woff
pypose_sphinx_theme/static/fonts/FreightSans/freight-sans-bold.woff2
pypose_sphinx_theme/static/fonts/FreightSans/freight-sans-book-italic.woff
pypose_sphinx_theme/static/fonts/FreightSans/freight-sans-book-italic.woff2
pypose_sphinx_theme/static/fonts/FreightSans/freight-sans-book.woff
pypose_sphinx_theme/static/fonts/FreightSans/freight-sans-book.woff2
pypose_sphinx_theme/static/fonts/FreightSans/freight-sans-light-italic.woff
pypose_sphinx_theme/static/fonts/FreightSans/freight-sans-light-italic.woff2
pypose_sphinx_theme/static/fonts/FreightSans/freight-sans-light.woff
pypose_sphinx_theme/static/fonts/FreightSans/freight-sans-light.woff2
pypose_sphinx_theme/static/fonts/FreightSans/freight-sans-medium-italic.woff
pypose_sphinx_theme/static/fonts/FreightSans/freight-sans-medium-italic.woff2
pypose_sphinx_theme/static/fonts/FreightSans/freight-sans-medium.woff
pypose_sphinx_theme/static/fonts/FreightSans/freight-sans-medium.woff2
pypose_sphinx_theme/static/fonts/IBMPlexMono/IBMPlexMono-Light.woff
pypose_sphinx_theme/static/fonts/IBMPlexMono/IBMPlexMono-Light.woff2
pypose_sphinx_theme/static/fonts/IBMPlexMono/IBMPlexMono-Medium.woff
pypose_sphinx_theme/static/fonts/IBMPlexMono/IBMPlexMono-Medium.woff2
pypose_sphinx_theme/static/fonts/IBMPlexMono/IBMPlexMono-Regular.woff
pypose_sphinx_theme-0.1.5.dist-info/LICENSE
pypose_sphinx_theme-0.1.5.dist-info/METADATA
pypose_sphinx_theme-0.1.5.dist-info/WHEEL
pypose_sphinx_theme-0.1.5.dist-info/entry_points.txt
pypose_sphinx_theme-0.1.5.dist-info/top_level.txt
pypose_sphinx_theme-0.1.5.dist-info/RECORD
